pqr/__init__.py
pqr/users.py
pqr/xyz/__init__.py
pqr/xyz/math.py
my_pqr_package-1.1.dist-info/METADATA
my_pqr_package-1.1.dist-info/WHEEL
my_pqr_package-1.1.dist-info/top_level.txt
my_pqr_package-1.1.dist-info/RECORD
