Metadata-Version: 2.1
Name: my-pqr-package
Version: 1.1
Summary: This Package is custom package with some functions
Author: Awnish Kumar
Author-email: awnishmmg.a41@gmail.com
